CHANGES
CONTRIBUTORS.txt
LICENSE
README.txt
bootstrap.py
buildout.cfg
setup.cfg
setup.py
iw/__init__.py
iw.recipe.sendmail.egg-info/PKG-INFO
iw.recipe.sendmail.egg-info/SOURCES.txt
iw.recipe.sendmail.egg-info/dependency_links.txt
iw.recipe.sendmail.egg-info/entry_points.txt
iw.recipe.sendmail.egg-info/namespace_packages.txt
iw.recipe.sendmail.egg-info/not-zip-safe
iw.recipe.sendmail.egg-info/requires.txt
iw.recipe.sendmail.egg-info/top_level.txt
iw/recipe/__init__.py
iw/recipe/sendmail/README.txt
iw/recipe/sendmail/__init__.py
iw/recipe/sendmail/template.zcml_tmpl
iw/recipe/sendmail/tests/__init__.py
iw/recipe/sendmail/tests/test_docs.py