Metadata-Version: 1.0
Name: iw.recipe.sendmail
Version: 0.2.3
Summary: ZC buildout recipe to setup zope.sendmail in a Zope2 instance
Home-page: http://plone.org/products/iw-recipes
Author: Ingeniweb
Author-email: support@ingeniweb.com
License: GPL
Keywords: plone zope smtp
Platform: UNKNOWN
Classifier: Framework :: Buildout
Classifier: Intended Audience :: Developers
Classifier: Topic :: Software Development :: Build Tools
Classifier: Topic :: Software Development :: Libraries :: Python Modules
Classifier: License :: OSI Approved :: GNU General Public License (GPL)
